spear_ai_ruff_config/__init__.py
spear_ai_ruff_config/config.toml
spear_ai_ruff_config-6.0.3.dist-info/METADATA
spear_ai_ruff_config-6.0.3.dist-info/WHEEL
spear_ai_ruff_config-6.0.3.dist-info/RECORD
