Metadata-Version: 2.4
Name: spear-ai-ruff-config
Version: 6.0.3
Summary: Spear AI’s Ruff config
Project-URL: Changelog, https://github.com/spear-ai/citizen/tree/main/packages/ruff-config/CHANGELOG.md
Project-URL: Documentation, https://github.com/spear-ai/citizen/tree/main/packages/ruff-config
Project-URL: Repository, https://github.com/spear-ai/citizen.git
Author-email: Spear AI <org@spear.ai>
License: MIT
Keywords: Ruff,Spear AI,config
Requires-Python: <3.13,>=3.10
Requires-Dist: ruff~=0.12
